.gitignore
DEFINES.yaml
README.md
generate_logging_tables.sql
setup.cfg
setup.py
outlook_emailer/__init__.py
outlook_emailer/main.py
outlook_emailer.egg-info/PKG-INFO
outlook_emailer.egg-info/SOURCES.txt
outlook_emailer.egg-info/dependency_links.txt
outlook_emailer.egg-info/requires.txt
outlook_emailer.egg-info/top_level.txt
tracker_site/application.py
tracker_site/static/logo.png
tracker_site/static/logo_large.png
tracker_site/static/routes.py