Metadata-Version: 1.1
Name: outlook-emailer
Version: 1.0.0
Summary: A package that provides a simple way of sending emails through Microsoft Exchange
Home-page: https://github.com/mwhamilton/outlook_emailer
Author: Matthew Hamilton
Author-email: mwhamilton6@gmail.com
License: MIT
Download-URL: https://github.com/mwhamilton/outlook_emailer/archive/1.0.0.tar.gz
Platform: UNKNOWN
Classifier: License :: OSI Approved :: MIT License
Classifier: Programming Language :: Python :: 3
Classifier: Programming Language :: Python :: 3.7
